ALU/alu.v
// Multiplexer module
module mux(output reg [15:0] out, input [15:0] in0, in1, in2, in3, in4, in5, in6, in7, in8, in9, in10, in11, in12, in13, in14, in15, input [3:0] sel);
  always @(*)
  begin  
    case (sel)  
      4'b0000: out = in0;
      4'b0001: out = in1;
      4'b0010: out = in2;
      4'b0011: out = in3;
      4'b0100: out = in4;
      4'b0101: out = in5;
      4'b0110: out = in6;
      4'b0111: out = in7;
      4'b1000: out = in8;
      4'b1001: out = in9;
      4'b1010: out = in10;
      4'b1011: out = in11;
      4'b1100: out = in12;
      4'b1101: out = in13;
      4'b1110: out = in14;
      4'b1111: out = in15;
      default: out = 8'bXXXXXXXX;
    endcase
  end
endmodule

module addition(
  output reg [15:0] result,
  input [15:0] a, b,
  input operation,  // 0: Add, 1: Subtract
  output reg Carry
);
  reg [16:0] full_sum;  // 17 bits to capture carry/borrow

  always @(*) begin
    if (operation == 0) begin
      // Addition
      full_sum = a + b;
      Carry = full_sum[16];  // Carry indicates overflow in addition
    end else begin
      // Subtraction (a - b)
      full_sum = {1'b0, a} + {1'b0, ~b} + 1'b1;  // a + (~b + 1)
      Carry = ~full_sum[16];  // Borrow occurred if Carry is 1
      full_sum= (Carry == 0)?full_sum:(~full_sum+1);

    end
    result = full_sum[15:0];  // Lower 16 bits as result
  end
endmodule



module multiplication(output [15:0] result, input [15:0] a, b);
assign result = a * b;
endmodule

module division(output [15:0] result, input [15:0] a, b);
assign result = a / b;
endmodule

module logical_and(output [15:0] result, input [15:0] a, b);
assign result = a && b;
endmodule

module logical_or(output [15:0] result, input [15:0] a, b);
assign result = a || b;
endmodule

module logical_not(output [15:0] result, input [15:0] a);
assign result = !a;
endmodule

module bitwise_and(output [15:0] result, input [15:0] a, b);
assign result = a & b;
endmodule

module bitwise_or(output [15:0] result, input [15:0] a, b);
assign result = a | b;
endmodule

module bitwise_xor(output [15:0] result, input [15:0] a, b);
assign result = a ^ b;
endmodule

module bitwise_not(output [15:0] result, input [15:0] a);
assign result = ~a;
endmodule

module right_shift(output [15:0] result, input [15:0] a);
assign result = a >> 1;
endmodule

module left_shift(output [15:0] result, input [15:0] a);
assign result = a << 1;
endmodule

module flags(
    output Sign, Zero, Parity, Overflow, 
    input [3:0] opcode, 
    input [15:0] a, b, Carry_in,op, output reg Carry_fin
);
  assign Sign = op[15]; 
  assign Zero = ~|op; 
  assign Parity = ~^op; 
  assign Overflow = (a[15] & b[15] & ~op[15]) | (~a[15] & ~b[15] & op[15]);
   always @(*) begin
    if (opcode == 4'b0000) begin
      Carry_fin=Carry_in[0]; // Addition
    end else if (opcode == 4'b0001) begin
      Carry_fin=Carry_in[1]; // Subtraction
    end else if (opcode == 4'b1110) begin
      Carry_fin=Carry_in[2]; // Inc
    end else if (opcode == 4'b1111) begin
       Carry_fin=Carry_in[3];// Dec
    end else begin
       Carry_fin= 1'b0; // Default result value
    end
  end

endmodule




module alu(output [15:0] op, 
           output Sign, Zero, Parity, Overflow, Carry_fin,
           input [15:0] a, b, 
           input [3:0] opcode);
  
  wire [15:0] add_result, sub_result, mul_result, div_result;
  wire [15:0] and_result, or_result, not_result;
  wire [15:0] bw_and_result, bw_or_result, bw_xor_result, bw_not_result;
  wire [15:0] rs_result, ls_result, inc_result, dec_result;
  
  wire [15:0] Carry;

  // Perform operations
  addition add(.result(add_result), .a(a), .b(b),.Carry(Carry[0]),.operation(1'b0));
  addition sub(.result(sub_result), .a(a), .b(b),.Carry(Carry[1]),.operation(1'b1));
  addition inc(.result(inc_result), .a(a),.b(16'h01),.Carry(Carry[2]),.operation(1'b0));
  addition dec(.result(dec_result), .a(a),.b(16'h01),.Carry(Carry[3]),.operation(1'b1));
  multiplication mul(.result(mul_result), .a(a), .b(b));
  division div(.result(div_result), .a(a), .b(b));

  logical_and land(.result(and_result), .a(a), .b(b));
  logical_or lor(.result(or_result), .a(a), .b(b));
  logical_not lnot(.result(not_result), .a(a));

  bitwise_and bwand(.result(bw_and_result), .a(a), .b(b));
  bitwise_or bwor(.result(bw_or_result), .a(a), .b(b));
  bitwise_xor bwxor(.result(bw_xor_result), .a(a), .b(b));
  bitwise_not bwnot(.result(bw_not_result), .a(a));

  right_shift rs(.result(rs_result), .a(a));
  left_shift ls(.result(ls_result), .a(a));

  // Multiplexer to select output
  mux result_mux(
    .out(op),
    .in0(add_result),
    .in1(sub_result),
    .in2(mul_result),
    .in3(div_result),
    .in4(16'b0),  // Placeholder for unused inputs
    .in5(bw_and_result),
    .in6(bw_or_result),
    .in7(and_result),
    .in8(or_result),
    .in9(bw_xor_result),
    .in10(bw_not_result),
    .in11(not_result),
    .in12(rs_result),
    .in13(ls_result),
    .in14(inc_result),
    .in15(dec_result),
    .sel(opcode)
  );

  // Flag logic
 flags flag_unit(.Carry_in(Carry),.Sign(Sign), .Zero(Zero), .Parity(Parity), .Overflow(Overflow), .op(op), .a(a), .b(b),.opcode(opcode),.Carry_fin(Carry_fin));

endmodule

ALU/alu_tb.v
`timescale 1ns / 1ps
`include "alu.v"
module alu_tb;
  // Inputs
  reg [15:0] a, b;
  reg [3:0] opcode;
  // Outputs
  wire [15:0] op;
  wire Sign, Zero, Parity, Overflow, Carry_fin;
  wire [15:0] Carry;

  // Instantiate the ALU module
  alu uut (
    .op(op),
    .Sign(Sign),
    .Zero(Zero),
    .Parity(Parity),
    .Overflow(Overflow),
    .Carry_fin(Carry_fin),
    .Carry(Carry),
    .a(a),
    .b(b),
    .opcode(opcode)
  );

  // Test vector procedure
  initial begin
    $dumpfile("alu_tb.vcd");
    $dumpvars(0, alu_tb);
    // Initialize inputs
    a = 16'h0000;
    b = 16'h0000;
    opcode = 4'b0000;  // Addition opcode

    // Apply Test Cases
    $display("Testing ALU Operations...\n");

    // Test: Addition (opcode 0000)
    a = 16'hffff;
    b = 16'h0003;
    opcode = 4'b0000;
    #10;
    $display("Addition: a = %h, b = %h, result = %h, Flags = {Sign=%b, Zero=%b, Parity=%b, Overflow=%b, Carry_fin=%b}", a, b, op, Sign, Zero, Parity, Overflow, Carry_fin);

    // Test: Subtraction (opcode 0001)
    a = 16'h0003;
    b = 16'h0005;  // Smaller to greater
    opcode = 4'b0001;
    #10;
    $display("Subtraction: a = %h, b = %h, result = %h, Flags = {Sign=%b, Zero=%b, Parity=%b, Overflow=%b, Carry_fin=%b}", a, b, op, Sign, Zero, Parity, Overflow, Carry_fin);

    // Test: Multiplication (opcode 0010)
    a = 16'h0004;
    b = 16'h0003;
    opcode = 4'b0010;
    #10;
    $display("Multiplication: a = %h, b = %h, result = %h, Flags = {Sign=%b, Zero=%b, Parity=%b, Overflow=%b, Carry_fin=%b}", a, b, op, Sign, Zero, Parity, Overflow, Carry_fin);

    // Test: Division (opcode 0011)
    a = 16'h0010;
    b = 16'h0002;
    opcode = 4'b0011;
    #10;
    $display("Division: a = %h, b = %h, result = %h, Flags = {Sign=%b, Zero=%b, Parity=%b, Overflow=%b, Carry_fin=%b}", a, b, op, Sign, Zero, Parity, Overflow, Carry_fin);

    // Test: Bitwise AND (opcode 0100)
    a = 16'hF0F0;
    b = 16'h0F0F;
    opcode = 4'b0101;
    #10;
    $display("Bitwise AND: a = %h, b = %h, result = %h, Flags = {Sign=%b, Zero=%b, Parity=%b, Overflow=%b, Carry_fin=%b}", a, b, op, Sign, Zero, Parity, Overflow, Carry_fin);

    // Test: Bitwise OR (opcode 0101)
    a = 16'hF0F0;
    b = 16'h0F0F;
    opcode = 4'b0110;
    #10;
    $display("Bitwise OR: a = %h, b = %h, result = %h, Flags = {Sign=%b, Zero=%b, Parity=%b, Overflow=%b, Carry_fin=%b}", a, b, op, Sign, Zero, Parity, Overflow, Carry_fin);

    // Test: Bitwise XOR (opcode 0110)
    a = 16'hF0F0;
    b = 16'h0F0F;
    opcode = 4'b1001;
    #10;
    $display("Bitwise XOR: a = %h, b = %h, result = %h, Flags = {Sign=%b, Zero=%b, Parity=%b, Overflow=%b, Carry_fin=%b}", a, b, op, Sign, Zero, Parity, Overflow, Carry_fin);

    // Test: Bitwise NOT (opcode 0111)
    a = 16'h0F0F;
    opcode = 4'b1010;
    #10;
    $display("Bitwise NOT: a = %h, result = %h, Flags = {Sign=%b, Zero=%b, Parity=%b, Overflow=%b, Carry_fin=%b}", a, op, Sign, Zero, Parity, Overflow, Carry_fin);

    // Test: Logical AND (opcode 1000)
    a = 16'h0001;
    b = 16'h0001;
    opcode = 4'b0111;
    #10;
    $display("Logical AND: a = %h, b = %h, result = %h, Flags = {Sign=%b, Zero=%b, Parity=%b, Overflow=%b, Carry_fin=%b}", a, b, op, Sign, Zero, Parity, Overflow, Carry_fin);

    // Test: Logical OR (opcode 1001)
    a = 16'h0001;
    b = 16'h0000;
    opcode = 4'b1000;
    #10;
    $display("Logical OR: a = %h, b = %h, result = %h, Flags = {Sign=%b, Zero=%b, Parity=%b, Overflow=%b, Carry_fin=%b}", a, b, op, Sign, Zero, Parity, Overflow, Carry_fin);

    // Test: Logical NOT (opcode 1010)
    a = 16'h0000;
    opcode = 4'b1011;
    #10;
    $display("Logical NOT: a = %h, result = %h, Flags = {Sign=%b, Zero=%b, Parity=%b, Overflow=%b, Carry_fin=%b}", a, op, Sign, Zero, Parity, Overflow, Carry_fin);

    // Test: Right Shift (opcode 1011)
    a = 16'h8000;
    opcode = 4'b1100;
    #10;
    $display("Right Shift: a = %h, result = %h, Flags = {Sign=%b, Zero=%b, Parity=%b, Overflow=%b, Carry_fin=%b}", a, op, Sign, Zero, Parity, Overflow, Carry_fin);

    // Test: Left Shift (opcode 1100)
    a = 16'h4000;
    opcode = 4'b1101;
    #10;
    $display("Left Shift: a = %h, result = %h, Flags = {Sign=%b, Zero=%b, Parity=%b, Overflow=%b, Carry_fin=%b}", a, op, Sign, Zero, Parity, Overflow, Carry_fin);

    // Test: Increment (opcode 1110)
    a = 16'h0001;
    opcode = 4'b1110;
    #10;
    $display("Increment: a = %h, result = %h, Flags = {Sign=%b, Zero=%b, Parity=%b, Overflow=%b, Carry_fin=%b}", a, op, Sign, Zero, Parity, Overflow, Carry_fin);

    // Test: Decrement (opcode 1111)
    a = 16'h0001;
    opcode = 4'b1111;
    #10;
    $display("Decrement: a = %h, result = %h, Flags = {Sign=%b, Zero=%b, Parity=%b, Overflow=%b, Carry_fin=%b}", a, op, Sign, Zero, Parity, Overflow, Carry_fin);

    // End of tests
    $finish;
  end

endmodule

ALU/alu_tb.vcd
$date
	Tue Jan 21 13:12:53 2025
$end
$version
	Icarus Verilog  
$end
$timescale
	1ps
$end
$scope module alu_tb $end
$var wire 16 ! op [15:0] $end
$var wire 1 " Zero $end
$var wire 1 # Sign $end
$var wire 1 $ Parity $end
$var wire 1 % Overflow $end
$var wire 1 & Carry_fin $end
$var wire 16 ' Carry [15:0] $end
$var reg 16 ( a [15:0] $end
$var reg 16 ) b [15:0] $end
$var reg 4 * opcode [3:0] $end
$scope module uut $end
$var wire 16 + a [15:0] $end
$var wire 16 , b [15:0] $end
$var wire 4 - opcode [3:0] $end
$var wire 16 . sub_result [15:0] $end
$var wire 16 / rs_result [15:0] $end
$var wire 16 0 or_result [15:0] $end
$var wire 16 1 op [15:0] $end
$var wire 16 2 not_result [15:0] $end
$var wire 16 3 mul_result [15:0] $end
$var wire 16 4 ls_result [15:0] $end
$var wire 16 5 inc_result [15:0] $end
$var wire 16 6 div_result [15:0] $end
$var wire 16 7 dec_result [15:0] $end
$var wire 16 8 bw_xor_result [15:0] $end
$var wire 16 9 bw_or_result [15:0] $end
$var wire 16 : bw_not_result [15:0] $end
$var wire 16 ; bw_and_result [15:0] $end
$var wire 16 < and_result [15:0] $end
$var wire 16 = add_result [15:0] $end
$var wire 1 " Zero $end
$var wire 1 # Sign $end
$var wire 1 $ Parity $end
$var wire 1 % Overflow $end
$var wire 1 & Carry_fin $end
$var wire 16 > Carry [15:0] $end
$scope module add $end
$var wire 16 ? a [15:0] $end
$var wire 16 @ b [15:0] $end
$var wire 1 A operation $end
$var reg 1 B Carry $end
$var reg 17 C full_sum [16:0] $end
$var reg 16 D result [15:0] $end
$upscope $end
$scope module bwand $end
$var wire 16 E a [15:0] $end
$var wire 16 F b [15:0] $end
$var wire 16 G result [15:0] $end
$upscope $end
$scope module bwnot $end
$var wire 16 H a [15:0] $end
$var wire 16 I result [15:0] $end
$upscope $end
$scope module bwor $end
$var wire 16 J a [15:0] $end
$var wire 16 K b [15:0] $end
$var wire 16 L result [15:0] $end
$upscope $end
$scope module bwxor $end
$var wire 16 M a [15:0] $end
$var wire 16 N b [15:0] $end
$var wire 16 O result [15:0] $end
$upscope $end
$scope module dec $end
$var wire 16 P a [15:0] $end
$var wire 16 Q b [15:0] $end
$var wire 1 R operation $end
$var reg 1 S Carry $end
$var reg 17 T full_sum [16:0] $end
$var reg 16 U result [15:0] $end
$upscope $end
$scope module div $end
$var wire 16 V a [15:0] $end
$var wire 16 W b [15:0] $end
$var wire 16 X result [15:0] $end
$upscope $end
$scope module flag_unit $end
$var wire 16 Y Carry_in [15:0] $end
$var wire 1 % Overflow $end
$var wire 16 Z a [15:0] $end
$var wire 16 [ b [15:0] $end
$var wire 4 \ opcode [3:0] $end
$var wire 16 ] op [15:0] $end
$var wire 1 " Zero $end
$var wire 1 # Sign $end
$var wire 1 $ Parity $end
$var reg 1 & Carry_fin $end
$upscope $end
$scope module inc $end
$var wire 16 ^ a [15:0] $end
$var wire 16 _ b [15:0] $end
$var wire 1 ` operation $end
$var reg 1 a Carry $end
$var reg 17 b full_sum [16:0] $end
$var reg 16 c result [15:0] $end
$upscope $end
$scope module land $end
$var wire 16 d a [15:0] $end
$var wire 16 e b [15:0] $end
$var wire 16 f result [15:0] $end
$upscope $end
$scope module lnot $end
$var wire 16 g a [15:0] $end
$var wire 16 h result [15:0] $end
$upscope $end
$scope module lor $end
$var wire 16 i a [15:0] $end
$var wire 16 j b [15:0] $end
$var wire 16 k result [15:0] $end
$upscope $end
$scope module ls $end
$var wire 16 l a [15:0] $end
$var wire 16 m result [15:0] $end
$upscope $end
$scope module mul $end
$var wire 16 n a [15:0] $end
$var wire 16 o b [15:0] $end
$var wire 16 p result [15:0] $end
$upscope $end
$scope module result_mux $end
$var wire 16 q in0 [15:0] $end
$var wire 16 r in10 [15:0] $end
$var wire 16 s in11 [15:0] $end
$var wire 16 t in13 [15:0] $end
$var wire 16 u in14 [15:0] $end
$var wire 16 v in15 [15:0] $end
$var wire 16 w in2 [15:0] $end
$var wire 16 x in3 [15:0] $end
$var wire 16 y in4 [15:0] $end
$var wire 16 z in5 [15:0] $end
$var wire 16 { in6 [15:0] $end
$var wire 16 | in7 [15:0] $end
$var wire 16 } in8 [15:0] $end
$var wire 16 ~ in9 [15:0] $end
$var wire 4 !" sel [3:0] $end
$var wire 16 "" in12 [15:0] $end
$var wire 16 #" in1 [15:0] $end
$var reg 16 $" out [15:0] $end
$upscope $end
$scope module rs $end
$var wire 16 %" a [15:0] $end
$var wire 16 &" result [15:0] $end
$upscope $end
$scope module sub $end
$var wire 16 '" a [15:0] $end
$var wire 16 (" b [15:0] $end
$var wire 1 )" operation $end
$var reg 1 *" Carry $end
$var reg 17 +" full_sum [16:0] $end
$var reg 16 ," result [15:0] $end
$upscope $end
$upscope $end
$upscope $end
$enddefinitions $end
$comment Show the parameter values. $end
$dumpall
$end
#0
$dumpvars
b1111111111111100 ,"
b11111111111111100 +"
0*"
1)"
b11 ("
b1111111111111111 '"
b111111111111111 &"
b1111111111111111 %"
b10 $"
b1111111111111100 #"
b111111111111111 ""
b0 !"
b1111111111111100 ~
b1 }
b1 |
b1111111111111111 {
b11 z
b0 y
b101010101010101 x
b1111111111111101 w
b1111111111111110 v
b0 u
b1111111111111110 t
b0 s
b0 r
b10 q
b1111111111111101 p
b11 o
b1111111111111111 n
b1111111111111110 m
b1111111111111111 l
b1 k
b11 j
b1111111111111111 i
b0 h
b1111111111111111 g
b1 f
b11 e
b1111111111111111 d
b0 c
b10000000000000000 b
1a
0`
b1 _
b1111111111111111 ^
b10 ]
b0 \
b11 [
b1111111111111111 Z
bz0101 Y
b101010101010101 X
b11 W
b1111111111111111 V
b1111111111111110 U
b11111111111111110 T
0S
1R
b1 Q
b1111111111111111 P
b1111111111111100 O
b11 N
b1111111111111111 M
b1111111111111111 L
b11 K
b1111111111111111 J
b0 I
b1111111111111111 H
b11 G
b11 F
b1111111111111111 E
b10 D
b10000000000000010 C
1B
0A
b11 @
b1111111111111111 ?
bz0101 >
b10 =
b1 <
b11 ;
b0 :
b1111111111111111 9
b1111111111111100 8
b1111111111111110 7
b101010101010101 6
b0 5
b1111111111111110 4
b1111111111111101 3
b0 2
b10 1
b1 0
b111111111111111 /
b1111111111111100 .
b0 -
b11 ,
b1111111111111111 +
b0 *
b11 )
b1111111111111111 (
bz0101 '
1&
0%
0$
0#
0"
b10 !
$end
#10000
b1000 =
b1000 D
b1000 q
0B
b1000 C
b1 ;
b1 G
b1 z
b1111111111111100 :
b1111111111111100 I
b1111111111111100 r
b111 9
b111 L
b111 {
b110 8
b110 O
b110 ~
b10 7
b10 U
b10 v
b10000000000000010 T
b100 5
b100 c
b100 u
0a
b100 b
b110 4
b110 m
b110 t
b1 /
b1 ""
b1 &"
b10 .
b10 #"
b10 ,"
bz0010 '
bz0010 >
bz0010 Y
1*"
b10000000000000010 +"
b1 *
b1 -
b1 \
b1 !"
b101 )
b101 ,
b101 @
b101 F
b101 K
b101 N
b101 W
b101 [
b101 e
b101 j
b101 o
b101 ("
b0 6
b0 X
b0 x
b1111 3
b1111 p
b1111 w
b11 (
b11 +
b11 ?
b11 E
b11 H
b11 J
b11 M
b11 P
b11 V
b11 Z
b11 ^
b11 d
b11 g
b11 i
b11 l
b11 n
b11 %"
b11 '"
#20000
0&
b111 =
b111 D
b111 q
b111 C
b0 ;
b0 G
b0 z
b1111111111111011 :
b1111111111111011 I
b1111111111111011 r
b111 8
b111 O
b111 ~
b11 7
b11 U
b11 v
b10000000000000011 T
b101 5
b101 c
b101 u
b101 b
b1000 4
b1000 m
b1000 t
1$
b1100 !
b1100 1
b1100 ]
b1100 $"
b10 /
b10 ""
b10 &"
b1 .
b1 #"
b1 ,"
bz0000 '
bz0000 >
bz0000 Y
0*"
b10000000000000001 +"
b10 *
b10 -
b10 \
b10 !"
b1 6
b1 X
b1 x
b11 )
b11 ,
b11 @
b11 F
b11 K
b11 N
b11 W
b11 [
b11 e
b11 j
b11 o
b11 ("
b1100 3
b1100 p
b1100 w
b100 (
b100 +
b100 ?
b100 E
b100 H
b100 J
b100 M
b100 P
b100 V
b100 Z
b100 ^
b100 d
b100 g
b100 i
b100 l
b100 n
b100 %"
b100 '"
#30000
b10010 =
b10010 D
b10010 q
b10010 C
b1111111111101111 :
b1111111111101111 I
b1111111111101111 r
b10010 9
b10010 L
b10010 {
b10010 8
b10010 O
b10010 ~
b1111 7
b1111 U
b1111 v
b10000000000001111 T
b10001 5
b10001 c
b10001 u
b10001 b
b100000 4
b100000 m
b100000 t
0$
b1000 !
b1000 1
b1000 ]
b1000 $"
b1000 /
b1000 ""
b1000 &"
b1110 .
b1110 #"
b1110 ,"
b10000000000001110 +"
b11 *
b11 -
b11 \
b11 !"
b10 )
b10 ,
b10 @
b10 F
b10 K
b10 N
b10 W
b10 [
b10 e
b10 j
b10 o
b10 ("
b1000 6
b1000 X
b1000 x
b100000 3
b100000 p
b100000 w
b10000 (
b10000 +
b10000 ?
b10000 E
b10000 H
b10000 J
b10000 M
b10000 P
b10000 V
b10000 Z
b10000 ^
b10000 d
b10000 g
b10000 i
b10000 l
b10000 n
b10000 %"
b10000 '"
#40000
b1111111111111111 =
b1111111111111111 D
b1111111111111111 q
b1111111111111111 C
b111100001111 :
b111100001111 I
b111100001111 r
b1111111111111111 9
b1111111111111111 L
b1111111111111111 {
b1111111111111111 8
b1111111111111111 O
b1111111111111111 ~
b1111000011101111 7
b1111000011101111 U
b1111000011101111 v
b11111000011101111 T
b1111000011110001 5
b1111000011110001 c
b1111000011110001 u
b1111000011110001 b
b1110000111100000 4
b1110000111100000 m
b1110000111100000 t
1$
1"
b0 !
b0 1
b0 ]
b0 $"
b111100001111000 /
b111100001111000 ""
b111100001111000 &"
b1110000111100001 .
b1110000111100001 #"
b1110000111100001 ,"
b11110000111100001 +"
b101 *
b101 -
b101 \
b101 !"
b111100001111 )
b111100001111 ,
b111100001111 @
b111100001111 F
b111100001111 K
b111100001111 N
b111100001111 W
b111100001111 [
b111100001111 e
b111100001111 j
b111100001111 o
b111100001111 ("
b10000 6
b10000 X
b10000 x
b10111000010000 3
b10111000010000 p
b10111000010000 w
b1111000011110000 (
b1111000011110000 +
b1111000011110000 ?
b1111000011110000 E
b1111000011110000 H
b1111000011110000 J
b1111000011110000 M
b1111000011110000 P
b1111000011110000 V
b1111000011110000 Z
b1111000011110000 ^
b1111000011110000 d
b1111000011110000 g
b1111000011110000 i
b1111000011110000 l
b1111000011110000 n
b1111000011110000 %"
b1111000011110000 '"
#50000
1#
0"
b1111111111111111 !
b1111111111111111 1
b1111111111111111 ]
b1111111111111111 $"
b110 *
b110 -
b110 \
b110 !"
#60000
b1001 *
b1001 -
b1001 \
b1001 !"
#70000
1%
1#
b1111000011110 =
b1111000011110 D
b1111000011110 q
b1111000011110 C
b111100001111 ;
b111100001111 G
b111100001111 z
b1111000011110000 :
b1111000011110000 I
b1111000011110000 r
b111100001111 9
b111100001111 L
b111100001111 {
b0 8
b0 O
b0 ~
b111100001110 7
b111100001110 U
b111100001110 v
b10000111100001110 T
b111100010000 5
b111100010000 c
b111100010000 u
b111100010000 b
b1111000011110 4
b1111000011110 m
b1111000011110 t
b1111000011110000 !
b1111000011110000 1
b1111000011110000 ]
b1111000011110000 $"
b11110000111 /
b11110000111 ""
b11110000111 &"
b0 .
b0 #"
b0 ,"
b10000000000000000 +"
b1010 *
b1010 -
b1010 \
b1010 !"
b1 6
b1 X
b1 x
b1100001011100001 3
b1100001011100001 p
b1100001011100001 w
b111100001111 (
b111100001111 +
b111100001111 ?
b111100001111 E
b111100001111 H
b111100001111 J
b111100001111 M
b111100001111 P
b111100001111 V
b111100001111 Z
b111100001111 ^
b111100001111 d
b111100001111 g
b111100001111 i
b111100001111 l
b111100001111 n
b111100001111 %"
b111100001111 '"
#80000
0%
0#
b10 =
b10 D
b10 q
b10 C
b1 ;
b1 G
b1 z
b1111111111111110 :
b1111111111111110 I
b1111111111111110 r
b1 9
b1 L
b1 {
b0 7
b0 U
b0 v
b10000000000000000 T
b10 5
b10 c
b10 u
b10 b
b10 4
b10 m
b10 t
0$
b1 !
b1 1
b1 ]
b1 $"
b0 /
b0 ""
b0 &"
b111 *
b111 -
b111 \
b111 !"
b1 )
b1 ,
b1 @
b1 F
b1 K
b1 N
b1 W
b1 [
b1 e
b1 j
b1 o
b1 ("
b1 6
b1 X
b1 x
b1 3
b1 p
b1 w
b1 (
b1 +
b1 ?
b1 E
b1 H
b1 J
b1 M
b1 P
b1 V
b1 Z
b1 ^
b1 d
b1 g
b1 i
b1 l
b1 n
b1 %"
b1 '"
#90000
b1 =
b1 D
b1 q
b1 C
b0 ;
b0 G
b0 z
b1 8
b1 O
b1 ~
b0 <
b0 f
b0 |
b1 .
b1 #"
b1 ,"
b10000000000000001 +"
b1000 *
b1000 -
b1000 \
b1000 !"
bx 6
bx X
bx x
b0 3
b0 p
b0 w
b0 )
b0 ,
b0 @
b0 F
b0 K
b0 N
b0 W
b0 [
b0 e
b0 j
b0 o
b0 ("
#100000
b0 =
b0 D
b0 q
b0 C
b1111111111111111 :
b1111111111111111 I
b1111111111111111 r
b0 9
b0 L
b0 {
b0 8
b0 O
b0 ~
b1 7
b1 U
b1 v
bz1000 '
bz1000 >
bz1000 Y
1S
b10000000000000001 T
b1 5
b1 c
b1 u
b1 b
b0 0
b0 k
b0 }
b0 4
b0 m
b0 t
b0 .
b0 #"
b0 ,"
b10000000000000000 +"
b1011 *
b1011 -
b1011 \
b1011 !"
b1 2
b1 h
b1 s
b0 (
b0 +
b0 ?
b0 E
b0 H
b0 J
b0 M
b0 P
b0 V
b0 Z
b0 ^
b0 d
b0 g
b0 i
b0 l
b0 n
b0 %"
b0 '"
#110000
b1000000000000000 =
b1000000000000000 D
b1000000000000000 q
b1000000000000000 C
b111111111111111 :
b111111111111111 I
b111111111111111 r
b1000000000000000 9
b1000000000000000 L
b1000000000000000 {
b1000000000000000 8
b1000000000000000 O
b1000000000000000 ~
b111111111111111 7
b111111111111111 U
b111111111111111 v
bz0000 '
bz0000 >
bz0000 Y
0S
b10111111111111111 T
b1000000000000001 5
b1000000000000001 c
b1000000000000001 u
b1000000000000001 b
b100000000000000 !
b100000000000000 1
b100000000000000 ]
b100000000000000 $"
b1 0
b1 k
b1 }
b100000000000000 /
b100000000000000 ""
b100000000000000 &"
b1000000000000000 .
b1000000000000000 #"
b1000000000000000 ,"
b11000000000000000 +"
b1100 *
b1100 -
b1100 \
b1100 !"
b0 2
b0 h
b0 s
b1000000000000000 (
b1000000000000000 +
b1000000000000000 ?
b1000000000000000 E
b1000000000000000 H
b1000000000000000 J
b1000000000000000 M
b1000000000000000 P
b1000000000000000 V
b1000000000000000 Z
b1000000000000000 ^
b1000000000000000 d
b1000000000000000 g
b1000000000000000 i
b1000000000000000 l
b1000000000000000 n
b1000000000000000 %"
b1000000000000000 '"
#120000
1%
1#
b1000000000000000 !
b1000000000000000 1
b1000000000000000 ]
b1000000000000000 $"
b100000000000000 =
b100000000000000 D
b100000000000000 q
b100000000000000 C
b1011111111111111 :
b1011111111111111 I
b1011111111111111 r
b100000000000000 9
b100000000000000 L
b100000000000000 {
b100000000000000 8
b100000000000000 O
b100000000000000 ~
b11111111111111 7
b11111111111111 U
b11111111111111 v
b10011111111111111 T
b100000000000001 5
b100000000000001 c
b100000000000001 u
b100000000000001 b
b1000000000000000 4
b1000000000000000 m
b1000000000000000 t
b10000000000000 /
b10000000000000 ""
b10000000000000 &"
b100000000000000 .
b100000000000000 #"
b100000000000000 ,"
b10100000000000000 +"
b1101 *
b1101 -
b1101 \
b1101 !"
b100000000000000 (
b100000000000000 +
b100000000000000 ?
b100000000000000 E
b100000000000000 H
b100000000000000 J
b100000000000000 M
b100000000000000 P
b100000000000000 V
b100000000000000 Z
b100000000000000 ^
b100000000000000 d
b100000000000000 g
b100000000000000 i
b100000000000000 l
b100000000000000 n
b100000000000000 %"
b100000000000000 '"
#130000
0%
0#
b10 !
b10 1
b10 ]
b10 $"
b1 =
b1 D
b1 q
b1 C
b1111111111111110 :
b1111111111111110 I
b1111111111111110 r
b1 9
b1 L
b1 {
b1 8
b1 O
b1 ~
b0 7
b0 U
b0 v
b10000000000000000 T
b10 5
b10 c
b10 u
b10 b
b10 4
b10 m
b10 t
b0 /
b0 ""
b0 &"
b1 .
b1 #"
b1 ,"
b10000000000000001 +"
b1110 *
b1110 -
b1110 \
b1110 !"
b1 (
b1 +
b1 ?
b1 E
b1 H
b1 J
b1 M
b1 P
b1 V
b1 Z
b1 ^
b1 d
b1 g
b1 i
b1 l
b1 n
b1 %"
b1 '"
#140000
1$
1"
b0 !
b0 1
b0 ]
b0 $"
b1111 *
b1111 -
b1111 \
b1111 !"
